clean_html_for_llm/__init__.py
clean_html_for_llm/clean_html_for_llm.py
clean_html_for_llm-1.3.0.dist-info/LICENSE
clean_html_for_llm-1.3.0.dist-info/METADATA
clean_html_for_llm-1.3.0.dist-info/WHEEL
clean_html_for_llm-1.3.0.dist-info/top_level.txt
clean_html_for_llm-1.3.0.dist-info/RECORD
