Metadata-Version: 2.1
Name: clean-html-for-llm
Version: 1.3.0
Summary: A library for cleaning HTML content by removing specified tags and attributes.
Home-page: https://github.com/yourusername/clean_html
Author: Shubham Raj
Author-email: sraj13169@gmail.com
License: MIT
Keywords: html cleaning,html cleaning for llm,html denoise for llm,html denoising for llm,html cleaning for language model,html denoise for language model,html denoising for language model,html cleaning for nlp,html denoise for nlp,html denoising for nlp
Classifier: Development Status :: 3 - Alpha
Classifier: Intended Audience :: Developers
Classifier: License :: OSI Approved :: MIT License
Classifier: Programming Language :: Python :: 3
Classifier: Programming Language :: Python :: 3.7
Classifier: Programming Language :: Python :: 3.8
Classifier: Programming Language :: Python :: 3.9
Requires-Python: >=3.7
License-File: LICENSE
